diffdir/ContentDirCmp.py
diffdir/__init__.py
diffdir/main.py
diffdir-0.9.1.dist-info/METADATA
diffdir-0.9.1.dist-info/WHEEL
diffdir-0.9.1.dist-info/entry_points.txt
diffdir-0.9.1.dist-info/top_level.txt
diffdir-0.9.1.dist-info/RECORD
