Metadata-Version: 2.1
Name: diffdir
Version: 0.9.1
Summary: Diff directories
Home-page: https://github.com/kjgfcdb/diffdir
Author: cdb
Author-email: kjgfcdb@126.com
License: MIT Licence
Platform: any
Requires-Dist: colorama
Requires-Dist: path
